tensorport
tensorport_cli
tf_runner
utils
version
