Metadata-Version: 1.2
Name: tensorport
Version: 1.5.5
Summary: TensorPort CLI and Python library.
Home-page: http://tensorport.com
Author: TensorPort
Author-email: info@tensorport.com
License: Apache Software License
Platform: UNKNOWN
Requires-Python: >2.6, !=3.0.*, !=3.1.*, !=3.2.*, <4
